Workbook

Sheet Assumptions
A1: Reserving Model - Key Assumptions
A3: Valuation date | B3: 2025-06-30
A4: Discount rate | B4: 0.035
A5: Expense loading | B5: 0.12
A6: Claims inflation | B6: 0.045
A7: FX rate HKD/USD | B7: 7.81
A10: Note: rates agreed with actuarial 14 Jul. Do not overwrite without sign-off.

Sheet Data
A1: Policy ID | B1: Line of Business | C1: Written Premium | D1: Earned Premium | E1: Region | G1: LOB Mapping
A2: POL-10002 | B2: Marine | C2: 85568.56 | D2: =C2*0.85 -> 72733.276 | E2: SG | G2: LOB Code | H2: LOB Name | I2: Reserve Factor
A3: POL-10003 | B3: Motor | C3: 11157.08 | D3: =C3*0.85 -> 9483.518 | E3: JP | G3: MTR | H3: Motor | I3: 0.62
A4: POL-10004 | B4: Motor | C4: 36083.56 | D4: =C4*0.85 -> 30671.026 | E4: HK | G4: PRP | H4: Property | I4: 0.48
A5: POL-10005 | B5: Property | C5: 8187.13 | D5: =C5*0.85 -> 6959.0605 | E5: SG | G5: MAR | H5: Marine | I5: 0.71
A6: POL-10006 | B6: Liability | C6: 10937.71 | D6: =C6*0.85 -> 9297.0535 | E6: HK | G6: LIA | H6: Liability | I6: 0.83
A7: POL-10007 | B7: Liability | C7: 10024.39 | D7: =C7*0.85 -> 8520.7315 | E7: JP
A8: POL-10008 | B8: Motor | C8: 85533.22 | D8: =C8*0.85 -> 72703.237 | E8: JP
A9: POL-10009 | B9: Motor | C9: 54053.75 | D9: =C9*0.85 -> 45945.688 | E9: SG
A10: POL-10010 | B10: Motor | C10: 87981.68 | D10: =C10*0.85 -> 74784.428 | E10: HK
A11: POL-10011 | B11: Property | C11: 29616.79 | D11: =C11*0.85 -> 25174.271 | E11: HK
A12: POL-10012 | B12: Motor | C12: 53527.66 | D12: =C12*0.85 -> 45498.511 | E12: JP
A13: POL-10013 | B13: Property | C13: 13759.74 | D13: =C13*0.85 -> 11695.779 | E13: JP
A14: POL-10014 | B14: Property | C14: 36653.79 | D14: =C14*0.85 -> 31155.721 | E14: JP
A15: POL-10015 | B15: Motor | C15: 52971.3 | D15: =C15*0.85 -> 45025.605 | E15: JP
A16: POL-10016 | B16: Property | C16: 47195.23 | D16: =C16*0.85 -> 40115.946 | E16: JP
A17: POL-10017 | B17: Liability | C17: 71064.45 | D17: =C17*0.85 -> 60404.783 | E17: SG
A18: POL-10018 | B18: Liability | C18: 35734.5 | D18: =C18*0.85 -> 30374.325 | E18: HK
... A41: POL-10041 | B41: Liability | C41: 86407.15 | D41: =C41*0.85 -> 73446.077 | E41: HK

Sheet Calc
A1: Reserve Roll-Forward
B3: Gross | D3: Reinsurance | F3: Net
A4: Accident Year | B4: Opening | C4: Movement | D4: Opening | E4: Movement | F4: Opening | G4: Movement
A5: 2019 | B5: 1331939 | C5: =B5*Assumptions!$B$6 -> 59937.255 | D5: =B5*0.3 -> 399581.7 | E5: =D5*Assumptions!$B$6 -> 17981.177 | F5: =B5-D5 -> 932357.3 | G5: =C5-E5 -> 41956.079 | I5: Adj factor
A6: 2020 | B6: 1605194 | C6: =B6*Assumptions!$B$6 -> 72233.73 | D6: =B6*0.3 -> 481558.2 | E6: =D6*Assumptions!$B$6 -> 21670.119 | F6: =B6-D6 -> 1123635.8 | G6: =C6-E6 -> 50563.611 | I6: 1.075
A7: 2021 | B7: 3634067 | C7: =B7*Assumptions!$B$6 -> 163533.02 | D7: =B7*0.3 -> 1090220.1 | E7: =D7*Assumptions!$B$6 -> 49059.904 | F7: =B7-D7 -> 2543846.9 | G7: =C7-E7 -> 114473.11 | I7: =I6*1.02 -> 1.0965
A8: 2022 | B8: 1048252 | C8: =B8*Assumptions!$B$6 -> 47171.34 | D8: =B8*0.3 -> 314475.6 | E8: =D8*Assumptions!$B$6 -> 14151.402 | F8: =B8-D8 -> 733776.4 | G8: =C8-E8 -> 33019.938
I9: 0
A10: 2023 | B10: 4324374 | C10: =B10*Assumptions!$B$6 -> 194596.83 | D10: =B10*0.3 -> 1297312.2 | E10: =D10*Assumptions!$B$6 -> 58379.049 | F10: =B10-D10 -> 3027061.8 | G10: =C10-E10 -> 136217.78 | I10: =I6/I9 -> #DIV/0!
A11: 2024 | B11: 1729371 | C11: =B11*Assumptions!$B$6 -> 77821.695 | D11: =B11*0.3 -> 518811.3 | E11: =D11*Assumptions!$B$6 -> 23346.508 | F11: =B11-D11 -> 1210559.7 | G11: =C11-E11 -> 54475.187
A12: 2025 | B12: 2127723 | C12: =B12*Assumptions!$B$6 -> 95747.535 | D12: =B12*0.3 -> 638316.9 | E12: =D12*Assumptions!$B$6 -> 28724.261 | F12: =B12-D12 -> 1489406.1 | G12: =C12-E12 -> 67023.274
A13: Total | B13: =SUM(B5:B8)+SUM(B10:B12) -> 15800920 | C13: =SUM(C5:C8)+SUM(C10:C12) -> 711041.4 | D13: =SUM(D5:D8)+SUM(D10:D12) -> 4740276 | E13: =SUM(E5:E8)+SUM(E10:E12) -> 213312.42 | F13: =SUM(F5:F8)+SUM(F10:F12) -> 11060644 | G13: =SUM(G5:G8)+SUM(G10:G12) -> 497728.98
A16: Notes:
A17: 2020 movement restated following audit query, see file Recon_2020_FINAL.xlsx

Sheet MI Pack
A1: Quarterly MI - Underwriting Result by Region
A3: Region | B3: Q1 | C3: Q2 | D3: Q3 | E3: Q4 | F3: FY
A4: HK | B4: -135809 | C4: 836477 | D4: 1024531 | E4: 296529 | F4: =SUM(B4:E4) -> 2021728
A5: SG | B5: -186271 | C5: 1648005 | D5: 1875560 | E5: 1137416 | F5: =SUM(B5:E5) -> 4474710
A6: JP | B6: 1349462 | C6: 641609 | D6: 1677449 | E6: 1879716 | F6: =SUM(B6:E6) -> 5548236
A7: AU | B7: 1201438 | C7: 898179 | D7: 495174 | E7: 485300 | F7: =SUM(B7:E7) -> 3080091

Sheet Old_Working
A1: scratch - do not use
A2: 0.48152282 | B2: =A2*2 -> 0.96304564
A3: 0.40044263 | B3: =A3*2 -> 0.80088526
A4: 0.19060954 | B4: =A4*2 -> 0.38121908
A5: 0.9846676 | B5: =A5*2 -> 1.9693352
A6: 0.44062687 | B6: =A6*2 -> 0.88125374
A7: 0.10992831 | B7: =A7*2 -> 0.21985661
A8: 0.60072726 | B8: =A8*2 -> 1.2014545
A9: 0.1023796 | B9: =A9*2 -> 0.2047592
A10: 0.56678361 | B10: =A10*2 -> 1.1335672
A11: 0.53661869 | B11: =A11*2 -> 1.0732374
A12: 0.94894876 | B12: =A12*2 -> 1.8978975
A13: 0.61373726 | B13: =A13*2 -> 1.2274745
... A19: 0.60227919 | B19: =A19*2 -> 1.2045584
